pysql_manager/__init__.py
pysql_manager/bases.py
pysql_manager/errors.py
pysql_manager/types.py
pysql_manager-0.1.1.dist-info/METADATA
pysql_manager-0.1.1.dist-info/WHEEL
pysql_manager-0.1.1.dist-info/top_level.txt
pysql_manager-0.1.1.dist-info/RECORD
