Metadata-Version: 2.1
Name: pysql-manager
Version: 0.1.1
Summary: A python package for managing Mysql
Home-page: https://github.com/Badhsuha/PysqlManager
Author: Badhusha K Muhammed
Author-email: badhushamuhammed09@gmail.com
License: BSD 2-clause
Platform: UNKNOWN
Classifier: Development Status :: 1 - Planning
Classifier: Intended Audience :: Developers
Classifier: License :: OSI Approved :: BSD License
Classifier: Operating System :: OS Independent
Classifier: Programming Language :: Python :: 3
Requires-Dist: mysql-connector-python
Requires-Dist: pandas
Requires-Dist: numpy
